yaml_config_manager/__init__.py
yaml_config_manager/config.py
yaml_config_manager-1.0.0.dist-info/LICENSE
yaml_config_manager-1.0.0.dist-info/METADATA
yaml_config_manager-1.0.0.dist-info/WHEEL
yaml_config_manager-1.0.0.dist-info/top_level.txt
yaml_config_manager-1.0.0.dist-info/RECORD
