Metadata-Version: 2.1
Name: yaml-config-manager
Version: 1.0.0
Summary: Small package for working with config files
Author: Guyshe
Project-URL: Homepage, https://github.com/guyshe/yaml-config-manager
Classifier: Programming Language :: Python :: 3
Classifier: License :: OSI Approved :: MIT License
Classifier: Operating System :: OS Independent
Requires-Python: >=3
License-File: LICENSE
Requires-Dist: PyYAML (~=5.4)
